LICENSE.txt
MANIFEST.in
README.rst
requirements.core.txt
requirements.txt
setup.py
core_explore_tree_app/__init__.py
core_explore_tree_app/admin.py
core_explore_tree_app/menus.py
core_explore_tree_app/settings.py
core_explore_tree_app/urls.py
core_explore_tree_app.egg-info/PKG-INFO
core_explore_tree_app.egg-info/SOURCES.txt
core_explore_tree_app.egg-info/dependency_links.txt
core_explore_tree_app.egg-info/requires.txt
core_explore_tree_app.egg-info/top_level.txt
core_explore_tree_app/commons/__init__.py
core_explore_tree_app/commons/enums.py
core_explore_tree_app/components/__init__.py
core_explore_tree_app/components/data/__init__.py
core_explore_tree_app/components/data/query.py
core_explore_tree_app/components/leaf/__init__.py
core_explore_tree_app/components/leaf/api.py
core_explore_tree_app/components/leaf/models.py
core_explore_tree_app/components/navigation/__init__.py
core_explore_tree_app/components/navigation/api.py
core_explore_tree_app/components/navigation/models.py
core_explore_tree_app/components/navigation/operations.py
core_explore_tree_app/components/query_ontology/__init__.py
core_explore_tree_app/components/query_ontology/api.py
core_explore_tree_app/components/query_ontology/models.py
core_explore_tree_app/parser/__init__.py
core_explore_tree_app/parser/parser.py
core_explore_tree_app/parser/processview.py
core_explore_tree_app/parser/renderer.py
core_explore_tree_app/rest/__init__.py
core_explore_tree_app/rest/urls.py
core_explore_tree_app/rest/query_ontology/__init__.py
core_explore_tree_app/rest/query_ontology/serializers.py
core_explore_tree_app/rest/query_ontology/views.py
core_explore_tree_app/static/core_explore_tree_app/admin/css/cache/style.css
core_explore_tree_app/static/core_explore_tree_app/admin/js/cache/load_cache_view.js
core_explore_tree_app/static/core_explore_tree_app/admin/js/query_ontology/list/activate.js
core_explore_tree_app/static/core_explore_tree_app/admin/js/query_ontology/list/activate.raw.js
core_explore_tree_app/static/core_explore_tree_app/admin/js/query_ontology/list/disable.js
core_explore_tree_app/static/core_explore_tree_app/admin/js/query_ontology/list/disable.raw.js
