Metadata-Version: 2.1
Name: core-explore-tree-app
Version: 1.6.0
Summary: Explore Tree app
Home-page: https://github.com/usnistgov/core_explore_tree_app
Author: NIST IT Lab
Author-email: itl_inquiries@nist.gov
License-File: LICENSE.txt
